tapenade/__init__.py
tapenade/data.py
tapenade/_tests/__init__.py
tapenade/analysis/__init__.py
tapenade/analysis/deformation/__init__.py
tapenade/analysis/deformation/additional_regionprops_properties.py
tapenade/analysis/deformation/deformation_quantification.py
tapenade/analysis/spatial_correlation/__init__.py
tapenade/analysis/spatial_correlation/_spatial_correlation_plotter.py
tapenade/notebooks/deformation_analysis_notebook.ipynb
tapenade/notebooks/masked_gaussian_smoothing_notebook.ipynb
tapenade/notebooks/preprocessing_notebook.ipynb
tapenade/notebooks/registration_notebook.ipynb
tapenade/notebooks/segmentation_notebook.ipynb
tapenade/notebooks/spatial_correlation_analysis_notebook.ipynb
tapenade/notebooks/spectral_filtering_notebook.ipynb
tapenade/notebooks/demo_data/.keep
tapenade/preprocessing/__init__.py
tapenade/preprocessing/_array_rescaling.py
tapenade/preprocessing/_axis_alignment.py
tapenade/preprocessing/_intensity_normalization.py
tapenade/preprocessing/_labels_masking.py
tapenade/preprocessing/_local_contrast_enhancement.py
tapenade/preprocessing/_preprocessing.py
tapenade/preprocessing/_segmentation.py
tapenade/preprocessing/_smoothing.py
tapenade/preprocessing/_thresholding.py
tapenade/preprocessing/segmentation_postprocessing.py
tapenade/preprocessing/_tests/__init__.py
tapenade/reconstruction/__init__.py
tapenade/reconstruction/_reconstruct.py
tapenade/segmentation/__init__.py
tapenade/segmentation/_segment.py
tapenade-0.0.21.dist-info/licenses/LICENSE
tapenade-0.0.21.dist-info/METADATA
tapenade-0.0.21.dist-info/WHEEL
tapenade-0.0.21.dist-info/entry_points.txt
tapenade-0.0.21.dist-info/top_level.txt
tapenade-0.0.21.dist-info/RECORD
