Metadata-Version: 2.4
Name: tapenade
Version: 0.0.21
Summary: A repository to process organoid images
Home-page: https://github.com/GuignardLab/tapenade
Author: Leo Guignard
Author-email: leo.guignard@univ-amu.fr
License: MIT
Project-URL: Bug Tracker, https://github.com/GuignardLab/tapenade/issues
Project-URL: Documentation, https://github.com/GuignardLab/tapenade#README.md
Project-URL: Source Code, https://github.com/GuignardLab/tapenade
Project-URL: User Support, https://github.com/GuignardLab/tapenade/issues
Classifier: Development Status :: 2 - Pre-Alpha
Classifier: Intended Audience :: Developers
Classifier: License :: OSI Approved :: MIT License
Classifier: Operating System :: OS Independent
Classifier: Programming Language :: Python
Classifier: Programming Language :: Python :: 3
Classifier: Programming Language :: Python :: 3 :: Only
Classifier: Programming Language :: Python :: 3.8
Classifier: Programming Language :: Python :: 3.9
Classifier: Programming Language :: Python :: 3.10
Classifier: Programming Language :: Python :: 3.11
Classifier: Topic :: Scientific/Engineering :: Image Processing
Requires-Python: >=3.8
License-File: LICENSE
Requires-Dist: scipy
Requires-Dist: jupyter
Requires-Dist: numba
Requires-Dist: numpy
Requires-Dist: scikit-image
Requires-Dist: scikit-learn
Requires-Dist: tifffile
Requires-Dist: matplotlib
Requires-Dist: 3d-registration>=0.5.2
Requires-Dist: tqdm
Provides-Extra: testing
Requires-Dist: tox; extra == "testing"
Requires-Dist: pytest; extra == "testing"
Requires-Dist: pytest-cov; extra == "testing"
Provides-Extra: dev
Requires-Dist: bumpver; extra == "dev"
Requires-Dist: ruff; extra == "dev"
Requires-Dist: black[jupyter]; extra == "dev"
Requires-Dist: pytest; extra == "dev"
Dynamic: license-file
